langspace/__init__.py
langspace/metrics/__init__.py
langspace/metrics/disentanglement.py
langspace/metrics/interpolation.py
langspace/models/__init__.py
langspace/ops/__init__.py
langspace/ops/arithmetic.py
langspace/ops/interpolation.py
langspace/ops/traversal.py
langspace/probe/__init__.py
langspace/probe/base.py
langspace/probe/arithmetic/__init__.py
langspace/probe/cluster_vis/__init__.py
langspace/probe/cluster_vis/methods.py
langspace/probe/defmod/__init__.py
langspace/probe/disentanglement/__init__.py
langspace/probe/interpolation/__init__.py
langspace/probe/lingprop/__init__.py
langspace/probe/sts/__init__.py
langspace/probe/traversal/__init__.py
langspace-0.3.7.dist-info/licenses/LICENSE
langspace-0.3.7.dist-info/METADATA
langspace-0.3.7.dist-info/WHEEL
langspace-0.3.7.dist-info/top_level.txt
langspace-0.3.7.dist-info/RECORD
